easyssl/__init__.py
easyssl/ca.py
easyssl/ssl.py
easyssl-1.0.3.dist-info/METADATA
easyssl-1.0.3.dist-info/WHEEL
easyssl-1.0.3.dist-info/top_level.txt
easyssl-1.0.3.dist-info/RECORD
