Metadata-Version: 2.1
Name: easyssl
Version: 1.0.3
Summary: Easy OpenSSL Utilities
Home-page: https://github.com/friendlyblackwell/easyssl
Author: Blackwell
Author-email: friendlyblackwell@example.com
Requires-Dist: PyYAML
